{
  "abort.html": "abort.html",
  "contact.html": "contact.html",
  "css/main.css": "css/main-83ca50552e37.css",
  "css/main.less": "css/main-4422e9a35e9c.less",
  "img/log.png": "img/log-a4a3533d54a3.png",
  "img/zx_00.png": "img/zx_00-5a5c8fe4c262.png",
  "img/zx_06.gif": "img/zx_06-b39232065473.gif",
  "img/zx_08.gif": "img/zx_08-2482f54f45ee.gif",
  "img/zx_11.gif": "img/zx_11-339c8cf4a1a3.gif",
  "img/zx_14.gif": "img/zx_14-aee58327588c.gif",
  "img/zx_17.gif": "img/zx_17-c60bbcbc9d80.gif",
  "img/zx_19.gif": "img/zx_19-e32d9fa9cf61.gif",
  "img/zx_21.gif": "img/zx_21-7471bddf02c2.gif",
  "img/zx_27.gif": "img/zx_27-432061b29134.gif",
  "img/zx_30.png": "img/zx_30-507022319a63.png",
  "index.html": "index.html",
  "js/main.js": "js/main-d41d8cd98f00.js",
  "shops.html": "shops.html"
}